<?xml version="1.0" encoding="utf-8" ?>
<AnimationSequence>
  <step>
    <option text="Check if injection spot is dry and clean." animation="CheckSkin" />
    <option text="Something" />
    <option text="Something" />
  </step>
  <step>
    <option text="Grab skin crease and lift the skin crease" animation="GrabGrease" />
    <option text="Something" />
    <option text="Something" />
  </step>
	<step>
		<option text="Inject needle straight in the injection spot" animation="InjectInsulin" />
		<option text="Inject neelde at a 45 degree angle" />
		<option text="Massage skin" />
	</step>
	<step>
		<option text="Fixate the insulinpen" animation="FixateInsulinPen" />
		<option text="Inject insulin" />
		<option text="Wait for 10 seconds" />
	</step>
	<step>
		<option text="Press the insulin pen button with thumb" animation="PressInsulinPen" />
		<option text="Wait for 10 seconds" />
		<option text="Vent the insulin pen" />
	</step>
	<step>
		<option text="Wait for 10 seconds" animation="WaitInsulinPen" />
		<option text="Pull needle out" />
		<option text="Wait for 5 minutes" />
	</step>
	<step>
		<option text="Pull the needle out of skin" animation="PullInsulinPen" />
		<option text="MassageSkin" />
		<option text="Take syringe off needle" />
	</step>
</AnimationSequence>